clinepunk/__init__.py
clinepunk/cache.py
clinepunk/cli.py
clinepunk/clinepunk.py
clinepunk/model.py
clinepunk/test.py
clinepunk/test2.py
clinepunk/words.py
clinepunk/words2.py
clinepunk/wordlists/words.txt
clinepunk/wordlists/words3.txt
clinepunk-0.1.14.dist-info/AUTHORS.rst
clinepunk-0.1.14.dist-info/LICENSE
clinepunk-0.1.14.dist-info/METADATA
clinepunk-0.1.14.dist-info/WHEEL
clinepunk-0.1.14.dist-info/entry_points.txt
clinepunk-0.1.14.dist-info/top_level.txt
clinepunk-0.1.14.dist-info/RECORD
