Metadata-Version: 2.1
Name: clinepunk
Version: 0.1.14
Summary: Python Boilerplate contains all the boilerplate you need to create a Python package.
Home-page: https://github.com/TaylorMonacelli/clinepunk
Author: Taylor Monacelli
Author-email: taylormonacelli@gmail.com
License: MIT license
Keywords: clinepunk
Platform: UNKNOWN
Classifier: Development Status :: 2 - Pre-Alpha
Classifier: Intended Audience :: Developers
Classifier: License :: OSI Approved :: MIT License
Classifier: Natural Language :: English
Classifier: Programming Language :: Python :: 3
Classifier: Programming Language :: Python :: 3.6
Classifier: Programming Language :: Python :: 3.7
Classifier: Programming Language :: Python :: 3.8
Requires-Python: >=3.6
License-File: LICENSE
License-File: AUTHORS.rst
Requires-Dist: appdirs
Requires-Dist: click
Requires-Dist: humanfriendly
Requires-Dist: requests
Requires-Dist: diskcache
Requires-Dist: importlib ; python_version == "3.7"
